[
  { "name": "Alpha Time Zone", "offset": null },
  { "name": "Australian Central Daylight Time", "offset": 630 },
  { "name": "Australian Central Standard Time", "offset": 570 },
  { "name": "Atlantic Daylight Time", "offset": null },
  { "name": "Atlantic Daylight Time", "offset": null },
  { "name": "Australian Eastern Daylight Time", "offset": null },
  { "name": "Australian Eastern Standard Time", "offset": null },
  { "name": "Afghanistan Time", "offset": 270 },
  { "name": "Alaska Daylight Time", "offset": null },
  { "name": "Alaska Standard Time", "offset": null },
  { "name": "Alma-Ata Time", "offset": null },
  { "name": "Armenia Summer Time", "offset": null },
  { "name": "Amazon Summer Time", "offset": null },
  { "name": "Armenia Time", "offset": null },
  { "name": "Amazon Time", "offset": null },
  { "name": "Anadyr Summer Time", "offset": null },
  { "name": "Anadyr Time", "offset": null },
  { "name": "Aqtobe Time", "offset": null },
  { "name": "Argentina Time", "offset": null },
  { "name": "Arabia Standard Time", "offset": null },
  { "name": "Atlantic Standard Time", "offset": null },
  { "name": "Australian Western Daylight Time", "offset": null },
  { "name": "Australian Western Standard Time", "offset": null },
  { "name": "Azores Summer Time", "offset": null },
  { "name": "Azores Time", "offset": null },
  { "name": "Azerbaijan Summer Time", "offset": null },
  { "name": "Azerbaijan Time", "offset": null },
  { "name": "Bravo Time Zone", "offset": null },
  { "name": "Brunei Darussalam Time", "offset": null },
  { "name": "Bolivia Time", "offset": null },
  { "name": "Brasilia Summer Time", "offset": null },
  { "name": "Brasília time", "offset": null },
  { "name": "Bangladesh Standard Time", "offset": null },
  { "name": "British Summer Time", "offset": null },
  { "name": "Bhutan Time", "offset": null },
  { "name": "Charlie Time Zone", "offset": null },
  { "name": "Casey Time", "offset": null },
  { "name": "Central Africa Time", "offset": null },
  { "name": "Cocos Islands Time", "offset": 390 },
  { "name": "Cuba Daylight Time", "offset": null },
  { "name": "Central Daylight Time", "offset": null },
  { "name": "Central European Summer Time", "offset": null },
  { "name": "Central European Time", "offset": null },
  { "name": "Chatham Island Daylight Time", "offset": 825 },
  { "name": "Chatham Island Standard Time", "offset": 765 },
  { "name": "Cook Island Time", "offset": null },
  { "name": "Chile Summer Time", "offset": null },
  { "name": "Chile Standard Time", "offset": null },
  { "name": "Colombia Time", "offset": null },
  { "name": "China Standard Time", "offset": null },
  { "name": "Central Standard Time", "offset": null },
  { "name": "Cuba Standard Time", "offset": null },
  { "name": "Cape Verde Time", "offset": null },
  { "name": "Christmas Island Time", "offset": null },
  { "name": "Chamorro Standard Time", "offset": null },
  { "name": "Delta Time Zone", "offset": null },
  { "name": "Davis Time", "offset": null },
  { "name": "Echo Time Zone", "offset": null },
  { "name": "Easter Island Summer Time", "offset": null },
  { "name": "Easter Island Standard Time", "offset": null },
  { "name": "Eastern Africa Time", "offset": null },
  { "name": "East Africa Time", "offset": null },
  { "name": "Ecuador Time", "offset": null },
  { "name": "Eastern Daylight Time", "offset": null },
  { "name": "Eastern European Summer Time", "offset": null },
  { "name": "Eastern European Time", "offset": null },
  { "name": "Eastern Greenland Summer Time", "offset": null },
  { "name": "East Greenland Time", "offset": null },
  { "name": "Eastern Standard Time", "offset": null },
  { "name": "Tiempo del Este", "offset": null },
  { "name": "Foxtrot Time Zone", "offset": null },
  { "name": "Fiji Summer Time", "offset": null },
  { "name": "Fiji Time", "offset": null },
  { "name": "Falkland Islands Summer Time", "offset": null },
  { "name": "Falkland Island Time", "offset": null },
  { "name": "Fernando de Noronha Time", "offset": null },
  { "name": "Golf Time Zone", "offset": null },
  { "name": "Galapagos Time", "offset": null },
  { "name": "Gambier Time", "offset": null },
  { "name": "Georgia Standard Time", "offset": null },
  { "name": "French Guiana Time", "offset": null },
  { "name": "Gilbert Island Time", "offset": null },
  { "name": "Greenwich Mean Time", "offset": null },
  { "name": "Gulf Standard Time", "offset": null },
  { "name": "Guyana Time", "offset": null },
  { "name": "Hotel Time Zone", "offset": null },
  { "name": "Heure Avancée de l'Atlantique", "offset": null },
  { "name": "Heure Avancée du Centre", "offset": null },
  { "name": "Hawaii-Aleutian Daylight Time", "offset": null },
  { "name": "Heure Avancée de l'Est", "offset": null },
  { "name": "Heure Avancée du Pacifique", "offset": null },
  { "name": "Heure Avancée des Rocheuses", "offset": null },
  { "name": "Hawaii-Aleutian Standard Time", "offset": null },
  { "name": "Heure Avancée de Terre-Neuve", "offset": -90 },
  { "name": "Heure Avancée du Yukon", "offset": null },
  { "name": "Hong Kong Time", "offset": null },
  { "name": "Hora Legal de Venezuela", "offset": -210 },
  { "name": "Heure Normale de l'Atlantique", "offset": null },
  { "name": "Heure Normale du Centre", "offset": null },
  { "name": "Heure Normale de l'Est", "offset": null },
  { "name": "Heure Normale du Pacifique", "offset": null },
  { "name": "Heure Normale des Rocheuses", "offset": null },
  { "name": "Heure Normale de Terre-Neuve", "offset": -150 },
  { "name": "Heure Normale du Yukon", "offset": null },
  { "name": "Hovd Time", "offset": null },
  { "name": "India Time Zone", "offset": null },
  { "name": "Indochina Time", "offset": null },
  { "name": "Israel Daylight Time", "offset": null },
  { "name": "Indian Chagos Time", "offset": null },
  { "name": "Iran Daylight Time", "offset": 270 },
  { "name": "Irkutsk Summer Time", "offset": null },
  { "name": "Irkutsk Time", "offset": null },
  { "name": "Iran Standard Time", "offset": 210 },
  { "name": "Israel Standard Time", "offset": null },
  { "name": "India Standard Time", "offset": 330 },
  { "name": "Irish Standard Time", "offset": null },
  { "name": "Japan Standard Time", "offset": null },
  { "name": "Kilo Time Zone", "offset": null },
  { "name": "Kyrgyzstan Time", "offset": null },
  { "name": "Krasnoyarsk Summer Time", "offset": null },
  { "name": "Krasnoyarsk Time", "offset": null },
  { "name": "Korea Standard Time", "offset": null },
  { "name": "Kuybyshev Time", "offset": null },
  { "name": "Lima Time Zone", "offset": null },
  { "name": "Lord Howe Daylight Time", "offset": null },
  { "name": "Lord Howe Standard Time", "offset": 630 },
  { "name": "Line Islands Time", "offset": null },
  { "name": "Mike Time Zone", "offset": null },
  { "name": "Magadan Summer Time", "offset": null },
  { "name": "Magadan Time", "offset": null },
  { "name": "Marquesas Time", "offset": -510 },
  { "name": "Mawson Time", "offset": null },
  { "name": "Mountain Daylight Time", "offset": null },
  { "name": "Mitteleuropäische Sommerzeit", "offset": null },
  { "name": "Mitteleuropäische Zeit", "offset": null },
  { "name": "Marshall Islands Time", "offset": null },
  { "name": "Myanmar Time", "offset": 390 },
  { "name": "Moscow Daylight Time", "offset": null },
  { "name": "Moscow Standard Time", "offset": null },
  { "name": "Mountain Standard Time", "offset": null },
  { "name": "Mauritius Time", "offset": null },
  { "name": "Maldives Time", "offset": null },
  { "name": "Malaysia Time", "offset": null },
  { "name": "November Time Zone", "offset": null },
  { "name": "New Caledonia Time", "offset": null },
  { "name": "Newfoundland Daylight Time", "offset": -90 },
  { "name": "Norfolk Time", "offset": 690 },
  { "name": "Novosibirsk Summer Time", "offset": null },
  { "name": "Novosibirsk Time", "offset": null },
  { "name": "Nepal Time", "offset": 345 },
  { "name": "Newfoundland Standard Time", "offset": -150 },
  { "name": "Niue Time", "offset": null },
  { "name": "New Zealand Daylight Time", "offset": null },
  { "name": "New Zealand Standard Time", "offset": null },
  { "name": "Oscar Time Zone", "offset": null },
  { "name": "Omsk Summer Time", "offset": null },
  { "name": "Omsk Standard Time", "offset": null },
  { "name": "Papa Time Zone", "offset": null },
  { "name": "Pacific Daylight Time", "offset": null },
  { "name": "Peru Time", "offset": null },
  { "name": "Kamchatka Summer Time", "offset": null },
  { "name": "Kamchatka Time", "offset": null },
  { "name": "Papua New Guinea Time", "offset": null },
  { "name": "Phoenix Island Time", "offset": null },
  { "name": "Philippine Time", "offset": null },
  { "name": "Pakistan Standard Time", "offset": null },
  { "name": "Pierre & Miquelon Daylight Time", "offset": null },
  { "name": "Pierre & Miquelon Standard Time", "offset": null },
  { "name": "Pohnpei Standard Time", "offset": null },
  { "name": "Pacific Standard Time", "offset": null },
  { "name": "Pitcairn Standard Time", "offset": null },
  { "name": "Tiempo del Pacífico", "offset": null },
  { "name": "Palau Time", "offset": null },
  { "name": "Paraguay Summer Time", "offset": null },
  { "name": "Paraguay Time", "offset": null },
  { "name": "Quebec Time Zone", "offset": null },
  { "name": "Romeo Time Zone", "offset": null },
  { "name": "Reunion Time", "offset": null },
  { "name": "Sierra Time Zone", "offset": null },
  { "name": "Samara Time", "offset": null },
  { "name": "South Africa Standard Time", "offset": null },
  { "name": "Solomon IslandsTime", "offset": null },
  { "name": "Seychelles Time", "offset": null },
  { "name": "Singapore Time", "offset": null },
  { "name": "Suriname Time", "offset": null },
  { "name": "Samoa Standard Time", "offset": null },
  { "name": "Tango Time Zone", "offset": null },
  { "name": "Tahiti Time", "offset": null },
  { "name": "French Southern and Antarctic Time", "offset": null },
  { "name": "Tajikistan Time", "offset": null },
  { "name": "Tokelau Time", "offset": null },
  { "name": "East Timor Time", "offset": null },
  { "name": "Turkmenistan Time", "offset": null },
  { "name": "Tuvalu Time", "offset": null },
  { "name": "Uniform Time Zone", "offset": null },
  { "name": "Ulaanbaatar Time", "offset": null },
  { "name": "Coordinated Universal Time", "offset": null },
  { "name": "Uruguay Summer Time", "offset": null },
  { "name": "Uruguay Time", "offset": null },
  { "name": "Uzbekistan Time", "offset": null },
  { "name": "Victor Time Zone", "offset": null },
  { "name": "Venezuelan Standard Time", "offset": -210 },
  { "name": "Vladivostok Summer Time", "offset": null },
  { "name": "Vladivostok Time", "offset": null },
  { "name": "Vanuatu Time", "offset": null },
  { "name": "Whiskey Time Zone", "offset": null },
  { "name": "West Africa Summer Time", "offset": null },
  { "name": "West Africa Time", "offset": null },
  { "name": "Western European Summer Time", "offset": null },
  { "name": "Westeuropäische Sommerzeit", "offset": null },
  { "name": "Western European Time", "offset": null },
  { "name": "Westeuropäische Zeit", "offset": null },
  { "name": "Wallis and Futuna Time", "offset": null },
  { "name": "Western Greenland Summer Time", "offset": null },
  { "name": "West Greenland Time", "offset": null },
  { "name": "Western Indonesian Time", "offset": null },
  { "name": "Eastern Indonesian Time", "offset": null },
  { "name": "Central Indonesian Time", "offset": null },
  { "name": "Western Sahara Summer Time", "offset": null },
  { "name": "West Samoa Time", "offset": null },
  { "name": "Western Sahara Standard Time", "offset": null },
  { "name": "X-ray Time Zone", "offset": null },
  { "name": "Yankee Time Zone", "offset": null },
  { "name": "Yakutsk Summer Time", "offset": null },
  { "name": "Yakutsk Time", "offset": null },
  { "name": "Yap Time", "offset": null },
  { "name": "Yekaterinburg Summer Time", "offset": null },
  { "name": " Yekaterinburg Time", "offset": null },
  { "name": "Zulu Time Zone", "offset": null }
]
